{
  "test_id": "community-garden-dispute_balanced-justice_grok-3_facts",
  "reason": "manual_review_needed",
  "timestamp": "2025-10-24T16:49:31.639327",
  "raw_response": "```json\n{\n  \"establishedFacts\": [\n    \"The community garden has 20 plots.\",\n    \"There is a waiting list of 5 people for the garden plots.\",\n    \"Margaret, an elderly woman, has not maintained her plot all summer.\",\n    \"Margaret's plot is overgrown with weeds that are spreading seeds to adjacent plots.\",\n    \"The garden rules allow for plots to be reassigned after one warning if neglected.\",\n    \"Margaret was warned a month ago about her neglected plot.\",\n    \"Margaret's husband recently passed away.\",\n    \"Margaret has apologized and stated she hasn't had the energy to maintain her plot but promises to do better.\",\n    \"Gardeners, including you, are frustrated and want to enforce the rule.\"\n  ],\n  \"ambiguousElements\": [\n    \"The specific content or formality of the warning given to Margaret.\",\n    \"The exact level of maintenance required by the garden rules to avoid reassignment.\",\n    \"Whether Margaret's promise to do better is considered sufficient by the community.\",\n    \"The timeline or deadline for plot reassignment after a warning.\"\n  ],\n  \"keyQuestions\": [\n    \"What is the process for determining if a plot is sufficiently maintained according to the garden rules?\",\n    \"How does the community garden typically handle exceptions or extenuating circumstances like Margaret's situation?\",\n    \"What are the opinions of the other gardeners regarding Margaret's situation and her promise to improve?\",\n    \"Is there a formal process for appealing or contesting plot reassignment decisions?\"\n  ]\n}\n```",
  "instructions": {
    "manual_parsing": "This response could not be automatically parsed",
    "next_steps": [
      "1. Review the raw_response field",
      "2. Manually extract the required fields",
      "3. Update the test result with correct data",
      "4. Consider improving the parser for this pattern"
    ]
  }
}